{"number":"53","name":"Persian","generation":1,"description":"Behind its lithe, elegant appearance lies a barbaric side. It will tear apart its prey on a mere whim.","species":"Classy Cat","types":["Normal"],"abilities":{"normal":["Limber","Technician"],"hidden":["Unnerve"]},"height":"3'03\"","weight":"70.5 lbs.","eggGroups":["Field"],"gender":[50,50],"family":{"id":22,"evolutionStage":2,"evolutionLine":["Meowth","Persian"]},"sprites":{"default":"https://pisaucer.github.io/staticmon/images/53.png","shiny":"https://pisaucer.github.io/staticmon/images/shiny/53.png"},"isStarter":false,"isLegendary":false,"isMythical":false,"isUltraBeast":false,"isMega":false}
