{"number":"333","name":"Swablu","generation":3,"description":"SWABLU has light and fluffy wings that are like cottony clouds. This POKéMON is not frightened of people. It lands on the heads of people and sits there like a cotton-fluff hat.","species":"Cotton Bird","types":["Normal","Flying"],"abilities":{"normal":["Natural Cure"],"hidden":["Cloud Nine"]},"height":"1'04\"","weight":"2.6 lbs.","eggGroups":["Flying","Dragon"],"gender":[50,50],"family":{"id":168,"evolutionStage":1,"evolutionLine":["Swablu","Altaria"]},"sprites":{"default":"https://pisaucer.github.io/staticmon/images/333.png","shiny":"https://pisaucer.github.io/staticmon/images/shiny/333.png"},"isStarter":false,"isLegendary":false,"isMythical":false,"isUltraBeast":false,"isMega":false}
