{
  "number": "179",
  "name": "Mareep",
  "generation": 2,
  "description": "It stores lots of air in its soft fur, allowing it to stay cool in summer and warm in winter.",
  "species": "Wool",
  "types": [
    "Electric"
  ],
  "abilities": {
    "normal": [
      "Static"
    ],
    "hidden": [
      "Plus"
    ]
  },
  "height": "2'",
  "weight": "17.2 lbs.",
  "eggGroups": [
    "Monster",
    "Field"
  ],
  "gender": [
    50,
    50
  ],
  "family": {
    "id": 89,
    "evolutionStage": 1,
    "evolutionLine": [
      "Mareep",
      "Flaaffy",
      "Ampharos"
    ]
  },
  "sprites": {
    "default": "https://pisaucer.github.io/staticmon/images/179.png",
    "shiny": "https://pisaucer.github.io/staticmon/images/shiny/179.png"
  },
  "isStarter": false,
  "isLegendary": false,
  "isMythical": false,
  "isUltraBeast": false,
  "isMega": false
}