{
  "number": "163",
  "name": "Hoothoot",
  "generation": 2,
  "description": "It begins to hoot at the same time every day. Some trainers use them in place of clocks.",
  "species": "Owl",
  "types": [
    "Normal",
    "Flying"
  ],
  "abilities": {
    "normal": [
      "Insomnia",
      "Keen Eye"
    ],
    "hidden": [
      "Tinted Lens"
    ]
  },
  "height": "2'04\"",
  "weight": "46.7 lbs.",
  "eggGroups": [
    "Flying"
  ],
  "gender": [
    50,
    50
  ],
  "family": {
    "id": 83,
    "evolutionStage": 1,
    "evolutionLine": [
      "Hoothoot",
      "Noctowl"
    ]
  },
  "sprites": {
    "default": "https://pisaucer.github.io/staticmon/images/163.png",
    "shiny": "https://pisaucer.github.io/staticmon/images/shiny/163.png"
  },
  "isStarter": false,
  "isLegendary": false,
  "isMythical": false,
  "isUltraBeast": false,
  "isMega": false
}